{"api-examples.md":"CrIOQ3n3","blog_computer_常用链接.md":"CA8MUd7f","blog_law_index.md":"CV5it_BP","blog_life_footprint_index.md":"CcZggvk7","blog_life_footprint_广州.md":"BphEOasG","blog_life_日记_2025年日记.md":"C1XIrYDO","blog_life_日记_2026年日记.md":"9rnVbuIK","blog_life_菜谱.md":"B2x_V1Kv","blog_read_books_为什么学生不喜欢学习.md":"C6Mi1oj4","blog_read_books_俗世奇人传.md":"BTSBXRbf","blog_read_books_哈佛大学积极心理学.md":"DRQJywg5","blog_read_books_哈利波特.md":"CkJMSagj","blog_read_books_太白金星有点烦.md":"CDuKbhyO","blog_read_books_张居正.md":"CFARUVW7","blog_read_books_我想要两颗西柚.md":"b_V7Dt-0","blog_read_books_我有自己的宇宙.md":"BZJbavog","blog_read_books_明朝那些事儿.md":"B0iJwyUU","blog_read_books_梁永安的爱情课.md":"C4niRCrm","blog_read_books_社会心理学.md":"4Gg--Dld","blog_read_books_繁花.md":"iyeyO9vR","blog_read_books_蛤蟆先生去看心理医生.md":"DNTUsk_t","blog_read_books_被讨厌的勇气.md":"TsUFZWPs","blog_read_books_读书的人.md":"n-FZQ85j","blog_read_books_身为女性的选择.md":"BAdZVUEn","blog_read_books_送你一颗子弹.md":"BKlbocvR","blog_read_books_重来3跳出疯狂的忙碌.md":"L6zfWlSZ","blog_read_books_阅读游历和爱情.md":"DRuUY4wh","blog_read_movies_心灵捕手.md":"CGXIkjC8","blog_read_movies_遇见你之前.md":"Ba9ua-Kr","blog_read_摘抄.md":"CWU9xDXh","blog_read_观影阅读记录.md":"Cjnr6eVn","blog_read_阮一峰期刊.md":"Da768i4R","blog_share_index.md":"DlSnaWxW","blog_sports_index.md":"CnaejpiE","index.md":"DtlORb6T","markdown-examples.md":"CfOg4Ljf"}
